a2a_llm_tracker/__init__.py
a2a_llm_tracker/__main__.py
a2a_llm_tracker/config.py
a2a_llm_tracker/context.py
a2a_llm_tracker/core.py
a2a_llm_tracker/events.py
a2a_llm_tracker/images.py
a2a_llm_tracker/meter.py
a2a_llm_tracker/middleware.py
a2a_llm_tracker/pricing.py
a2a_llm_tracker/response_analyzer.py
a2a_llm_tracker/integrations/__init__.py
a2a_llm_tracker/integrations/litellm.py
a2a_llm_tracker/sinks/__init__.py
a2a_llm_tracker/sinks/base.py
a2a_llm_tracker/sinks/ccs.py
a2a_llm_tracker/sinks/console.py
a2a_llm_tracker/sinks/jsonl.py
a2a_llm_tracker/sinks/sqlite.py
a2a_llm_tracker/sources/__init__.py
a2a_llm_tracker/sources/ccs_source.py
a2a_llm_tracker-0.0.22.dist-info/METADATA
a2a_llm_tracker-0.0.22.dist-info/WHEEL
a2a_llm_tracker-0.0.22.dist-info/top_level.txt
a2a_llm_tracker-0.0.22.dist-info/RECORD
